setup.py
admt_distributions/Binomialdistribution.py
admt_distributions/Gaussiandistribution.py
admt_distributions/Generaldistribution.py
admt_distributions/__init__.py
admt_distributions.egg-info/PKG-INFO
admt_distributions.egg-info/SOURCES.txt
admt_distributions.egg-info/dependency_links.txt
admt_distributions.egg-info/not-zip-safe
admt_distributions.egg-info/top_level.txt