Metadata-Version: 1.0
Name: admt-distributions
Version: 1.1
Summary: Gaussian and Binomial distributions
Home-page: UNKNOWN
Author: Ayush Deval
Author-email: ayush.deval2017@gmail.com
License: UNKNOWN
Platform: UNKNOWN
